shrunk/__init__.py
shrunk/api/__init__.py
shrunk/api/admin.py
shrunk/api/alert.py
shrunk/api/link.py
shrunk/api/linkhub.py
shrunk/api/org.py
shrunk/api/position.py
shrunk/api/request.py
shrunk/api/role.py
shrunk/api/role_request.py
shrunk/api/search.py
shrunk/api/security.py
shrunk/api/user.py
shrunk/ci-test-config.py
shrunk/client/__init__.py
shrunk/client/aggregations.py
shrunk/client/alerts.py
shrunk/client/exceptions.py
shrunk/client/geoip.py
shrunk/client/linkhub.py
shrunk/client/links.py
shrunk/client/orgs.py
shrunk/client/positions.py
shrunk/client/role_requests.py
shrunk/client/roles.py
shrunk/client/search.py
shrunk/client/security.py
shrunk/client/tracking.py
shrunk/client/users.py
shrunk/config.py.example
shrunk/dev_logins.py
shrunk/linkhub_viewer.py
shrunk/local-test-config.py
shrunk/sso.py
shrunk/static/css/geist.css
shrunk/static/css/static.css
shrunk/static/dist/index.11a9b6f2.js
shrunk/static/dist/index.11dc89d2.css
shrunk/static/dist/index.4a8e5c23.js
shrunk/static/dist/index.html
shrunk/static/dist/linkhub-loader.5a989651.js
shrunk/static/dist/linkhub-loader.html
shrunk/static/fonts/Geist-Black.ttf
shrunk/static/fonts/Geist-Bold.ttf
shrunk/static/fonts/Geist-ExtraBold.ttf
shrunk/static/fonts/Geist-ExtraLight.ttf
shrunk/static/fonts/Geist-Light.ttf
shrunk/static/fonts/Geist-Medium.ttf
shrunk/static/fonts/Geist-Regular.ttf
shrunk/static/fonts/Geist-SemiBold.ttf
shrunk/static/fonts/Geist-Thin.ttf
shrunk/static/img/favicon.ico
shrunk/static/img/pixel.gif
shrunk/static/img/pixel.png
shrunk/static/img/preview.png
shrunk/static/img/rutgers.png
shrunk/static/img/rutgers.svg
shrunk/templates/404.html
shrunk/templates/access_request_resolved.html
shrunk/templates/base.html
shrunk/templates/help_no_2fa.html
shrunk/templates/html/role_requests/approval.html
shrunk/templates/html/role_requests/confirmation.html
shrunk/templates/html/role_requests/denial.html
shrunk/templates/html/role_requests/notification.html
shrunk/templates/login.html
shrunk-2.4.7.dist-info/WHEEL
shrunk-2.4.7.dist-info/METADATA
shrunk-2.4.7.dist-info/RECORD
