Metadata-Version: 2.1
Name: shrunk
Version: 2.4.7
Summary: URL Shortener for Rutgers University
Home-page: https://github.com/oss/shrunk
License: MIT
Author: Rutgers Open System Solutions
Author-email: oss@oit.rutgers.edu
Maintainer: Andrew Hong
Maintainer-email: ah1371@oit.rutgers.edu
Requires-Python: >=3.6,<4.0
Classifier: Development Status :: 5 - Production/Stable
Classifier: License :: OSI Approved :: MIT License
Classifier: Programming Language :: Python :: 3
Classifier: Programming Language :: Python :: 3.10
Classifier: Programming Language :: Python :: 3.6
Classifier: Programming Language :: Python :: 3.7
Classifier: Programming Language :: Python :: 3.8
Classifier: Programming Language :: Python :: 3.9
Requires-Dist: backports-datetime-fromisoformat (==1.0.0)
Requires-Dist: backports_datetime_fromisoformat (==1.0.0)
Requires-Dist: click (==7.0)
Requires-Dist: flask (==1.1.2)
Requires-Dist: flask-mailman (==0.1.7)
Requires-Dist: flask-sso (==0.4.0)
Requires-Dist: geoip2 (==2.9.0)
Requires-Dist: httpagentparser (==1.9.0)
Requires-Dist: itsdangerous (==1.1.0)
Requires-Dist: jinja2 (==2.11.3)
Requires-Dist: jsonschema (==3.2.0)
Requires-Dist: markupsafe (==1.1.1)
Requires-Dist: pillow (==8.4.0)
Requires-Dist: pymongo (==3.11.0)
Requires-Dist: python-ldap (>=3.4.4,<4.0.0)
Requires-Dist: requests (==2.17.3)
Requires-Dist: segno (>=1.6.1,<2.0.0)
Requires-Dist: six (>=1.16.0,<2.0.0)
Requires-Dist: slack-sdk (==3.27.1)
Requires-Dist: werkzeug (==1.0.1)
Project-URL: Repository, https://github.com/oss/shrunk
